topless/__init__.py
topless/actions/dispatcher.py
topless/actions/envelopes.py
topless/actions/handler.py
topless/actions/middlewares.py
topless/actions/response.py
topless/app.py
topless/bootstrap.py
topless/config.py
topless/entrypoint.py
topless/errors.py
topless/logger.py
topless/models/__init__.py
topless/models/base.py
topless/models/connection.py
topless/models/exceptions.py
topless/models/orm/manager.py
topless/models/orm/mapper.py
topless/models/orm/queryset.py
topless/models/utils.py
topless/payloads.py
topless/schemas.py
topless/utils/aws.py
topless/utils/words.py
topless-0.1.0.dist-info/METADATA
topless-0.1.0.dist-info/WHEEL
topless-0.1.0.dist-info/entry_points.txt
topless-0.1.0.dist-info/RECORD
