Metadata-Version: 2.1
Name: topless
Version: 0.1.0
Summary: Tailored OPerations for serverLESS
Author: Rafael Izidoro
Author-email: izidoro.me@gmail.com
Requires-Python: >=3.11,<4.0
Classifier: Programming Language :: Python :: 3
Classifier: Programming Language :: Python :: 3.11
Requires-Dist: alembic (>=1.12.1,<2.0.0)
Requires-Dist: aws-lambda-powertools (>=2.26.0,<3.0.0)
Requires-Dist: boto3 (>=1.28.67,<2.0.0)
Requires-Dist: jinja2 (>=3.1.2,<4.0.0)
Requires-Dist: marshmallow (>=3.20.1,<4.0.0)
Requires-Dist: marshmallow-dataclass[enum,union] (>=8.6.0,<9.0.0)
Requires-Dist: pg8000 (>=1.30.3,<2.0.0)
Requires-Dist: pluralizer (>=1.2.0,<2.0.0)
Requires-Dist: requests (>=2.31.0,<3.0.0)
Requires-Dist: requests-aws-sign (>=0.1.6,<0.2.0)
Requires-Dist: rich (>=13.7.0,<14.0.0)
Requires-Dist: ruamel-yaml (>=0.18.5,<0.19.0)
Requires-Dist: sqlalchemy (>=2.0.23,<3.0.0)
Requires-Dist: strenum (>=0.4.15,<0.5.0)
Requires-Dist: stringcase (>=1.2.0,<2.0.0)
Requires-Dist: tomli (>=2.0.1,<3.0.0)
Requires-Dist: typer (>=0.9.0,<0.10.0)
Requires-Dist: uuid6 (>=2023.5.2,<2024.0.0)
